sphinx_intl/__init__.py
sphinx_intl/__main__.py
sphinx_intl/basic.py
sphinx_intl/catalog.py
sphinx_intl/commands.py
sphinx_intl/pycompat.py
sphinx_intl/sphinx_util.py
sphinx_intl/transifex.py
sphinx_intl-2.3.1.dist-info/AUTHORS.rst
sphinx_intl-2.3.1.dist-info/LICENSE
sphinx_intl-2.3.1.dist-info/METADATA
sphinx_intl-2.3.1.dist-info/WHEEL
sphinx_intl-2.3.1.dist-info/entry_points.txt
sphinx_intl-2.3.1.dist-info/top_level.txt
sphinx_intl-2.3.1.dist-info/RECORD
