Metadata-Version: 2.1
Name: sphinx-intl
Version: 2.3.1
Summary: Sphinx utility that make it easy to translate and to apply translation.
Author-email: Takayuki SHIMIZUKAWA <shimizukawa@gmail.com>
License: BSD 2-Clause License
Project-URL: Homepage, https://github.com/sphinx-doc/sphinx-intl
Project-URL: Documentation, https://sphinx-intl.readthedocs.io
Classifier: Development Status :: 5 - Production/Stable
Classifier: Environment :: Console
Classifier: License :: OSI Approved :: BSD License
Classifier: Topic :: Documentation
Classifier: Topic :: Documentation :: Sphinx
Classifier: Topic :: Software Development
Classifier: Topic :: Software Development :: Documentation
Classifier: Topic :: Text Processing
Classifier: Topic :: Text Processing :: General
Classifier: Topic :: Utilities
Classifier: Operating System :: OS Independent
Classifier: Programming Language :: Python :: 3.9
Classifier: Programming Language :: Python :: 3.10
Classifier: Programming Language :: Python :: 3.11
Classifier: Programming Language :: Python :: 3.12
Classifier: Programming Language :: Python :: 3.13
Classifier: Framework :: Sphinx
Requires-Python: >=3.9
License-File: LICENSE
License-File: AUTHORS.rst
Requires-Dist: setuptools
Requires-Dist: click
Requires-Dist: babel
Requires-Dist: sphinx
Provides-Extra: test
Requires-Dist: pytest; extra == "test"
